CHANGELOG.md
CONTRIBUTING.md
LICENSE.md
docker/Dockerfile
docker/app_config.yaml
docker/docker-compose.yaml
docker/docker-entrypoint.sh
docker/supervisord.conf
docs/CHANGELOG.md
docs/CONTRIBUTING.md
docs/LICENSE.md
docs/README.md
docs/conf.py
docs/deploy.md
docs/index.rst
docs/ms_graph_exporter.celery.rst
docs/ms_graph_exporter.ms_graph.rst
docs/ms_graph_exporter.rst
ms_graph_exporter/__init__.py
ms_graph_exporter/celery/__init__.py
ms_graph_exporter/celery/app.py
ms_graph_exporter/celery/config.py
ms_graph_exporter/celery/graph_api_base.py
ms_graph_exporter/celery/tasks.py
ms_graph_exporter/ms_graph/__init__.py
ms_graph_exporter/ms_graph/api.py
ms_graph_exporter/ms_graph/response.py
tests/__init__.py
tests/conftest.py
tox.ini
ms_graph_exporter-0.1.0rc4.dev201910092.dist-info/LICENSE.md
ms_graph_exporter-0.1.0rc4.dev201910092.dist-info/WHEEL
ms_graph_exporter-0.1.0rc4.dev201910092.dist-info/METADATA
ms_graph_exporter-0.1.0rc4.dev201910092.dist-info/RECORD
