Metadata-Version: 2.1
Name: ms-graph-exporter
Version: 0.1.0rc4.dev201910092
Summary: A distributed Celery application to export time-domain data periodically from Microsoft Graph API into a buffer key-value store.
Home-page: https://github.com/undp/MsGraphExporter
License: MIT
Keywords: development,monitoring,microsoft graph
Author: Oleksiy Kuzmenko
Author-email: oleksiy.kuzmenko@undp.org
Requires-Python: >=3.6,<4.0
Classifier: Development Status :: 4 - Beta
Classifier: Environment :: No Input/Output (Daemon)
Classifier: Intended Audience :: Developers
Classifier: Intended Audience :: System Administrators
Classifier: License :: OSI Approved :: MIT License
Classifier: Natural Language :: English
Classifier: Operating System :: POSIX :: Linux
Classifier: Programming Language :: Python :: 3
Classifier: Programming Language :: Python :: 3.6
Classifier: Programming Language :: Python :: 3.7
Classifier: Topic :: System :: Monitoring
Provides-Extra: docs
Provides-Extra: test
Requires-Dist: adal (>=1.2,<2.0)
Requires-Dist: celery (>=4.3,<5.0)
Requires-Dist: celery-redbeat (>=0.13,<0.14)
Requires-Dist: gevent (>=1.4,<2.0)
Requires-Dist: pytest (>=5.1,<6.0); extra == "test"
Requires-Dist: pytest-benchmark[aspect] (>=3.2,<4.0); extra == "test"
Requires-Dist: pytest-cov (>=2.7,<3.0); extra == "test"
Requires-Dist: pytest-dockerc (>=1.0,<2.0); extra == "test"
Requires-Dist: pytest-instafail (>=0.4,<0.5); extra == "test"
Requires-Dist: pytest-lazy-fixture (>=0.5,<0.6); extra == "test"
Requires-Dist: pytest-random-order (>=1.0,<2.0); extra == "test"
Requires-Dist: pyyaml (>=3.13,<4.0)
Requires-Dist: recommonmark (>=0.5.0,<0.6.0); extra == "docs"
Requires-Dist: redis (>=3.3,<4.0)
Requires-Dist: requests (>=2.20,<3.0)
Requires-Dist: sphinx (>=2.2,<3.0); extra == "docs"
Requires-Dist: sphinx-autodoc-typehints (>=1.8,<2.0); extra == "docs"
Requires-Dist: sphinx-rtd-theme (>=0.4,<0.5)
Requires-Dist: typing (>=3.7,<4.0)
Project-URL: Documentation, https://msgraphexporter.readthedocs.io/en/latest/
Project-URL: Repository, https://github.com/undp/MsGraphExporter
